andrew_confidence_intervals
