Metadata-Version: 2.1
Name: andrew-confidence-intervals
Version: 0.0.6
Summary: Package for calculation of confidence intervals.
Home-page: https://github.com/Cliefspring/andrew_confidence_intervals
Author: Andrey Vazhentsev
Author-email: vazhentsev@inbox.ru
License: MIT
Keywords: confidence intervals
Platform: UNKNOWN
Classifier: Development Status :: 5 - Production/Stable
Classifier: Intended Audience :: Science/Research
Classifier: Operating System :: Microsoft :: Windows :: Windows 10
Classifier: License :: OSI Approved :: MIT License
Classifier: Programming Language :: Python :: 3
